AUTHORS
LICENSE
MANIFEST.in
README.rst
setup.py
Flask_Espresso.egg-info/PKG-INFO
Flask_Espresso.egg-info/SOURCES.txt
Flask_Espresso.egg-info/dependency_links.txt
Flask_Espresso.egg-info/not-zip-safe
Flask_Espresso.egg-info/requires.txt
Flask_Espresso.egg-info/top_level.txt
flask_espresso/__init__.py
flask_espresso/coffee-script.js
flask_espresso/coffeescript.py
flask_espresso/espresso.py