Metadata-Version: 1.1
Name: Flask-Espresso
Version: 0.1.1
Summary: Adds Coffescript support to Flask applications
Home-page: https://github.com/morgan-del/flask-espresso
Author: Morgan Delahaye-Prat
Author-email: mdp@m-del.net
License: BSD
Platform: any
Classifier: Development Status :: 4 - Beta
Classifier: Environment :: Web Environment
Classifier: Intended Audience :: Developers
Classifier: License :: OSI Approved :: BSD License
Classifier: Operating System :: OS Independent
Classifier: Programming Language :: Python
Classifier: Programming Language :: Python :: 3
Classifier: Topic :: Internet :: WWW/HTTP :: Dynamic Content
Classifier: Topic :: Software Development :: Libraries :: Python Modules
